{
    "ApprovalTime": "2016-07-01T16:25:18Z",
    "AutoApprovalTime": "2016-07-01T16:24:55Z",
    "AssignmentId": "3PEIJLRY6TTHB0HJPKP4G0446NUWXY",
    "WorkerId": "APG8FREAKLXMG",
    "answers": {
        "data": {
            "domain": [
                "restaurant"
            ],
            "scale": [
                "training",
                "training",
                "special_unique",
                "liked_loved",
                "memorable_unforgettable",
                "good_excellent",
                "bad_terrible",
                "memorable_unforgettable",
                "liked_loved",
                "disliked_hated",
                "disliked_hated",
                "good_excellent",
                "special_unique",
                "bad_terrible"
            ],
            "language": [
                "english"
            ],
            "degree": [
                "strong",
                "weak",
                "strong",
                "strong",
                "strong",
                "weak",
                "weak",
                "weak",
                "weak",
                "strong",
                "weak",
                "strong",
                "weak",
                "strong"
            ],
            "gender": [
                "female"
            ],
            "age": [
                "31"
            ],
            "expt_aim": [
                "Not sure"
            ],
            "expt_gen": [
                "nope"
            ],
            "alt3": [
                "lower",
                "higher",
                "coporate",
                "loathed",
                "bland",
                "terrible",
                "special",
                "imemorable",
                "regretted",
                "enjoyed",
                "loved",
                "forgettable ",
                "crowded",
                "amazing"
            ],
            "alt2": [
                "higher",
                "lower",
                "boring",
                "liked",
                "forgettable",
                "great",
                "great",
                "boring",
                "loathed",
                "liked",
                "enjoyed",
                "subpar",
                "popular",
                "wonderful"
            ],
            "alt1": [
                "low",
                "high",
                "unimaginative",
                "hated",
                "memorable",
                "bad",
                "good",
                "forgettable",
                "hated",
                "loved",
                "liked",
                "terrible",
                "cool",
                "great"
            ]
        }
    },
    "AcceptTime": "2016-07-01T16:13:48Z",
    "HITId": "31J7RYECZLQQNLMXOBSTNWO0UCO1LS",
    "Assignment": "",
    "AssignmentStatus": "Approved",
    "SubmitTime": "2016-07-01T16:19:55Z"
}