{
    "ApprovalTime": "2016-07-03T14:56:18Z",
    "AutoApprovalTime": "2016-07-03T14:55:22Z",
    "AssignmentId": "34YB12FSQYOAK2SFW8JDJG2I5XYMGN",
    "WorkerId": "A5340TSPQX0L4",
    "answers": {
        "data": {
            "domain": [
                "game"
            ],
            "scale": [
                "training",
                "training",
                "liked_loved",
                "bad_terrible",
                "disliked_hated",
                "bad_terrible",
                "memorable_unforgettable",
                "good_excellent",
                "disliked_hated",
                "liked_loved",
                "special_unique",
                "special_unique",
                "memorable_unforgettable",
                "good_excellent"
            ],
            "language": [
                "English"
            ],
            "degree": [
                "strong",
                "weak",
                "strong",
                "weak",
                "strong",
                "strong",
                "weak",
                "weak",
                "weak",
                "weak",
                "weak",
                "strong",
                "strong",
                "strong"
            ],
            "gender": [
                "male"
            ],
            "age": [
                "19"
            ],
            "expt_aim": [
                "Adjectives"
            ],
            "expt_gen": [
                ""
            ],
            "alt3": [
                "poor",
                "awesome",
                "loathed",
                "perfect",
                "liked",
                "perfect",
                "bad",
                "mediocre",
                "enjoyed",
                "loathed",
                "regular",
                "same",
                "long-lasting",
                "bad"
            ],
            "alt2": [
                "mediocre",
                "great",
                "disliked",
                "good",
                "adored",
                "amazing",
                "forgetful",
                "terrible",
                "loved",
                "hated",
                "ordinary",
                "regular",
                "amazing",
                "poor"
            ],
            "alt1": [
                "low",
                "high",
                "hated",
                "great",
                "loved",
                "great",
                "unmemorable",
                "bad",
                "liked",
                "disliked",
                "unspecial",
                "ununique",
                "unforgetful",
                "terrible"
            ]
        }
    },
    "AcceptTime": "2016-07-03T14:46:53Z",
    "HITId": "3KTCJ4SCVG1AT34IONT8N93PUHNM1O",
    "Assignment": "",
    "AssignmentStatus": "Approved",
    "SubmitTime": "2016-07-03T14:50:22Z"
}