{
    "ApprovalTime": "2016-07-02T00:28:18Z",
    "AutoApprovalTime": "2016-07-02T00:27:33Z",
    "AssignmentId": "38BQUHLA9W0YCF9DKRWLOPBKWIPOMA",
    "WorkerId": "A2JRONMDBUJT3K",
    "answers": {
        "data": {
            "domain": [
                "movie"
            ],
            "scale": [
                "training",
                "training",
                "good_excellent",
                "special_unique",
                "disliked_hated",
                "disliked_hated",
                "liked_loved",
                "special_unique",
                "memorable_unforgettable",
                "good_excellent",
                "bad_terrible",
                "memorable_unforgettable",
                "bad_terrible",
                "liked_loved"
            ],
            "language": [
                "english"
            ],
            "degree": [
                "strong",
                "weak",
                "strong",
                "weak",
                "strong",
                "weak",
                "weak",
                "strong",
                "weak",
                "weak",
                "strong",
                "strong",
                "weak",
                "strong"
            ],
            "gender": [
                "female"
            ],
            "age": [
                "22"
            ],
            "expt_aim": [
                "how people use synonyms"
            ],
            "expt_gen": [
                ""
            ],
            "alt3": [
                "GOOD",
                "poor",
                "astounding",
                "unique",
                "boring",
                "bad",
                "interesting",
                "good",
                "quality",
                "interesting",
                "mundane",
                "worthy",
                "boring",
                "good"
            ],
            "alt2": [
                "STELLAR",
                "negative",
                "attention ",
                "original",
                "bad",
                "poor",
                "happy",
                "original",
                "interesting",
                "amazing",
                "boring",
                "thrilling",
                "bad",
                "enticing"
            ],
            "alt1": [
                "POSITIVE",
                "bad",
                "amazing",
                "interesting",
                "horrible",
                "negative",
                "good",
                "clever",
                "shocking",
                "quality",
                "horrible",
                "interesting",
                "horrible",
                "captivating"
            ]
        }
    },
    "AcceptTime": "2016-07-02T00:19:48Z",
    "HITId": "3XEIP58NL0NNIH75WM1LFQ8C7R2ZLG",
    "Assignment": "",
    "AssignmentStatus": "Approved",
    "SubmitTime": "2016-07-02T00:22:33Z"
}