{"ApprovalTime": "2016-07-01T16:27:18Z", "AutoApprovalTime": "2016-07-01T16:26:36Z", "AssignmentId": "3OE22WJIGIOKAZR286FB44NEO4WUQ0", "WorkerId": "anon33", "answers": {"data": {"domain": ["restaurant"], "scale": ["training", "training", "disliked_hated", "disliked_hated", "liked_loved", "special_unique", "memorable_unforgettable", "bad_terrible", "bad_terrible", "special_unique", "good_excellent", "memorable_unforgettable", "good_excellent", "liked_loved"], "language": ["English"], "degree": ["strong", "weak", "weak", "strong", "weak", "weak", "weak", "weak", "strong", "strong", "strong", "strong", "weak", "strong"], "gender": ["male"], "age": ["28"], "expt_aim": ["words that we choose"], "expt_gen": [""], "alt3": ["bad", "good", "enjoyed", "enjoyed", "abhored", "average", "boring", "perfect", "enjoyable", "common", "average", "common", "normal", "unloved"], "alt2": ["poor", "fantastic", "loved", "liked", "disliked", "boring", "non-memorable", "excellent", "nice", "boring", "horrible", "average", "average", "disliked"], "alt1": ["low", "high", "liked", "loved", "hated", "unspecial", "average", "good", "good", "average", "bad", "forgettable", "bad", "hated"]}}, "AcceptTime": "2016-07-01T16:17:07Z", "HITId": "31J7RYECZLQQNLMXOBSTNWO0UCO1LS", "Assignment": "", "AssignmentStatus": "Approved", "SubmitTime": "2016-07-01T16:21:36Z"}